DE_Lib/__init__.py
DE_Lib/Cloud/__init__.py
DE_Lib/DATAx/Parametros.py
DE_Lib/DATAx/__init__.py
DE_Lib/DataBase/Azure.py
DE_Lib/DataBase/Cache.py
DE_Lib/DataBase/Firebird.py
DE_Lib/DataBase/Informix.py
DE_Lib/DataBase/Metadata.py
DE_Lib/DataBase/MsSql.py
DE_Lib/DataBase/MySql.py
DE_Lib/DataBase/Oracle.py
DE_Lib/DataBase/OracleDDL.py
DE_Lib/DataBase/Postgres.py
DE_Lib/DataBase/RedShift.py
DE_Lib/DataBase/SQCipher.py
DE_Lib/DataBase/SQLite.py
DE_Lib/DataBase/__init__.py
DE_Lib/Files/Avro.py
DE_Lib/Files/Csv.py
DE_Lib/Files/JSon.py
DE_Lib/Files/Parquet.py
DE_Lib/Files/Txt.py
DE_Lib/Files/Xlsx.py
DE_Lib/Files/Zip.py
DE_Lib/Files/__init__.py
DE_Lib/Log/DE_LogEventos.py
DE_Lib/Log/Level.py
DE_Lib/Log/Log.py
DE_Lib/Log/__init__.py
DE_Lib/Utils/Colors.py
DE_Lib/Utils/DateUtils.py
DE_Lib/Utils/Email.py
DE_Lib/Utils/Generic.py
DE_Lib/Utils/Sql.py
DE_Lib/Utils/System.py
DE_Lib/Utils/WebHook.py
DE_Lib/Utils/__init__.py
DE_Lib/Utils/Cipher/Aes.py
DE_Lib/Utils/Cipher/Argon.py
DE_Lib/Utils/Cipher/Base64.py
DE_Lib/Utils/Cipher/Cipher.py
DE_Lib/Utils/Cipher/Fernet.py
DE_Lib/Utils/Cipher/Gcm.py
DE_Lib/Utils/Cipher/Pbkdf2.py
DE_Lib/Utils/Cipher/Rsa.py
DE_Lib/Utils/Cipher/__init__.py
de_lib-0.0.56.3.3.dist-info/licenses/LICENCE
de_lib-0.0.56.3.3.dist-info/METADATA
de_lib-0.0.56.3.3.dist-info/WHEEL
de_lib-0.0.56.3.3.dist-info/top_level.txt
de_lib-0.0.56.3.3.dist-info/RECORD
