Metadata-Version: 2.4
Name: DE_Lib
Version: 0.0.56.3.3
Summary: Biblioteca de funcionalidades
Home-page: https://github.com/DE-DataEng/DE_Lib.git
Author: Almir J Gomes
Author-email: almir.jg@hotmail.com
License-File: LICENCE
Requires-Dist: cx_Oracle
Requires-Dist: oracledb>=3.2.0
Requires-Dist: pymssql>=1.1.1
Requires-Dist: JayDeBeApi
Requires-Dist: mysql.connector
Requires-Dist: psycopg2
Requires-Dist: pywinauto==0.6.9
Requires-Dist: cryptography==45.0.5
Requires-Dist: redshift-connector
Requires-Dist: SQLAlchemy==2.0.38
Requires-Dist: bcrypt==4.3.0
Requires-Dist: argon2-cffi==23.1.0
Requires-Dist: pyautogui
Dynamic: author
Dynamic: author-email
Dynamic: description
Dynamic: description-content-type
Dynamic: home-page
Dynamic: license-file
Dynamic: requires-dist
Dynamic: summary
